mysql_server_has_gone_away/__init__.py
mysql_server_has_gone_away/base.py
mysql_server_has_gone-2.0.5.dist-info/LICENSE
mysql_server_has_gone-2.0.5.dist-info/METADATA
mysql_server_has_gone-2.0.5.dist-info/WHEEL
mysql_server_has_gone-2.0.5.dist-info/top_level.txt
mysql_server_has_gone-2.0.5.dist-info/RECORD
