Metadata-Version: 2.1
Name: mysql_server_has_gone
Version: 2.0.5
Summary: Django myslq backend that fixes issue with long living connection
Home-page: https://github.com/maiyajj/MySQL-server-has-gone-away
Author: maiyajj
Author-email: 1045373828@qq.com
License: MIT
License-File: LICENSE
